{
  "date": "2025-12-11",
  "sourcePath": "2025/12/2025-12-11-19:15.pdf",
  "rates": {
    "USD": 89.95,
    "AED": 24.01,
    "AUD": 58.87,
    "BDT": 0,
    "BHD": 232.4,
    "CAD": 64.64,
    "CHF": 111.1,
    "CNY": 0,
    "DKK": 14.02,
    "EUR": 104.3,
    "GBP": 119.4,
    "HKD": 11.53,
    "JPY": 0.573,
    "KES": 0,
    "KRW": 0,
    "KWD": 287,
    "LKR": 0,
    "MYR": 0,
    "NOK": 8.87,
    "NZD": 51.3,
    "OMR": 228.6,
    "PKR": 0,
    "QAR": 23.51,
    "RUB": 0,
    "SAR": 23.59,
    "SEK": 9.67,
    "SGD": 68.94,
    "THB": 2.6,
    "TRY": 0,
    "ZAR": 5.2
  }
}