[
  {
    "date": "2025-09-01",
    "rate": 22.87
  },
  {
    "date": "2025-09-02",
    "rate": 22.75
  },
  {
    "date": "2025-09-03",
    "rate": 23.6
  },
  {
    "date": "2025-09-04",
    "rate": 23.6
  },
  {
    "date": "2025-09-05",
    "rate": 23.6
  },
  {
    "date": "2025-09-06",
    "rate": 23.61
  },
  {
    "date": "2025-09-07",
    "rate": 23.61
  },
  {
    "date": "2025-09-08",
    "rate": 23.57
  },
  {
    "date": "2025-09-09",
    "rate": 23.58
  },
  {
    "date": "2025-09-10",
    "rate": 22.69
  },
  {
    "date": "2025-09-11",
    "rate": 22.83
  },
  {
    "date": "2025-09-12",
    "rate": 22.95
  },
  {
    "date": "2025-09-13",
    "rate": 22.95
  },
  {
    "date": "2025-09-14",
    "rate": 22.95
  },
  {
    "date": "2025-09-15",
    "rate": 22.78
  },
  {
    "date": "2025-09-16",
    "rate": 23.59
  },
  {
    "date": "2025-09-17",
    "rate": 22.82
  },
  {
    "date": "2025-09-18",
    "rate": 22.72
  },
  {
    "date": "2025-09-19",
    "rate": 23.63
  },
  {
    "date": "2025-09-20",
    "rate": 22.84
  },
  {
    "date": "2025-09-21",
    "rate": 22.84
  },
  {
    "date": "2025-09-22",
    "rate": 22.86
  },
  {
    "date": "2025-09-23",
    "rate": 23.74
  },
  {
    "date": "2025-09-24",
    "rate": 23.71
  },
  {
    "date": "2025-09-25",
    "rate": 22.94
  },
  {
    "date": "2025-09-26",
    "rate": 22.81
  },
  {
    "date": "2025-09-27",
    "rate": 22.81
  },
  {
    "date": "2025-09-28",
    "rate": 22.81
  },
  {
    "date": "2025-09-29",
    "rate": 22.98
  },
  {
    "date": "2025-10-01",
    "rate": 23.79
  },
  {
    "date": "2025-10-02",
    "rate": 23.79
  },
  {
    "date": "2025-10-03",
    "rate": 23.75
  },
  {
    "date": "2025-10-04",
    "rate": 23.76
  },
  {
    "date": "2025-10-05",
    "rate": 23.76
  },
  {
    "date": "2025-10-06",
    "rate": 22.91
  },
  {
    "date": "2025-10-07",
    "rate": 23.78
  },
  {
    "date": "2025-10-08",
    "rate": 22.87
  },
  {
    "date": "2025-10-09",
    "rate": 22.95
  },
  {
    "date": "2025-10-10",
    "rate": 22.77
  },
  {
    "date": "2025-10-11",
    "rate": 22.77
  },
  {
    "date": "2025-10-12",
    "rate": 22.77
  },
  {
    "date": "2025-10-13",
    "rate": 22.98
  },
  {
    "date": "2025-10-14",
    "rate": 22.89
  },
  {
    "date": "2025-10-15",
    "rate": 22.88
  },
  {
    "date": "2025-10-16",
    "rate": 23.52
  },
  {
    "date": "2025-10-17",
    "rate": 22.81
  },
  {
    "date": "2025-10-18",
    "rate": 22.7
  },
  {
    "date": "2025-10-19",
    "rate": 22.7
  },
  {
    "date": "2025-10-20",
    "rate": 22.69
  },
  {
    "date": "2025-10-21",
    "rate": 22.69
  },
  {
    "date": "2025-10-22",
    "rate": 22.69
  },
  {
    "date": "2025-10-23",
    "rate": 22.74
  },
  {
    "date": "2025-10-24",
    "rate": 22.76
  },
  {
    "date": "2025-10-25",
    "rate": 22.76
  },
  {
    "date": "2025-10-26",
    "rate": 22.76
  },
  {
    "date": "2025-10-27",
    "rate": 22.78
  },
  {
    "date": "2025-10-28",
    "rate": 23.66
  },
  {
    "date": "2025-10-29",
    "rate": 22.79
  },
  {
    "date": "2025-10-30",
    "rate": 23.74
  },
  {
    "date": "2025-10-31",
    "rate": 22.86
  },
  {
    "date": "2025-11-01",
    "rate": 23.76
  },
  {
    "date": "2025-11-02",
    "rate": 23.76
  },
  {
    "date": "2025-11-03",
    "rate": 22.87
  },
  {
    "date": "2025-11-04",
    "rate": 23.71
  },
  {
    "date": "2025-11-05",
    "rate": 23.71
  },
  {
    "date": "2025-11-06",
    "rate": 23.73
  },
  {
    "date": "2025-11-07",
    "rate": 22.93
  },
  {
    "date": "2025-11-08",
    "rate": 22.93
  },
  {
    "date": "2025-11-09",
    "rate": 22.93
  },
  {
    "date": "2025-11-10",
    "rate": 22.93
  },
  {
    "date": "2025-11-11",
    "rate": 22.9
  },
  {
    "date": "2025-11-12",
    "rate": 22.85
  },
  {
    "date": "2025-11-13",
    "rate": 23.75
  },
  {
    "date": "2025-11-14",
    "rate": 23.76
  },
  {
    "date": "2025-11-15",
    "rate": 23.77
  },
  {
    "date": "2025-11-16",
    "rate": 23.77
  },
  {
    "date": "2025-11-17",
    "rate": 22.92
  },
  {
    "date": "2025-11-18",
    "rate": 22.9
  },
  {
    "date": "2025-11-19",
    "rate": 22.89
  },
  {
    "date": "2025-11-20",
    "rate": 22.78
  },
  {
    "date": "2025-11-21",
    "rate": 23.15
  },
  {
    "date": "2025-11-22",
    "rate": 23.15
  },
  {
    "date": "2025-11-23",
    "rate": 23.15
  },
  {
    "date": "2025-11-24",
    "rate": 23.06
  },
  {
    "date": "2025-11-25",
    "rate": 22.92
  },
  {
    "date": "2025-11-26",
    "rate": 23.9
  },
  {
    "date": "2025-11-27",
    "rate": 23.9
  },
  {
    "date": "2025-11-28",
    "rate": 23.11
  },
  {
    "date": "2025-11-29",
    "rate": 23.17
  },
  {
    "date": "2025-11-30",
    "rate": 23.17
  },
  {
    "date": "2025-12-01",
    "rate": 23.27
  },
  {
    "date": "2025-12-02",
    "rate": 23.1
  },
  {
    "date": "2025-12-03",
    "rate": 23.29
  },
  {
    "date": "2025-12-04",
    "rate": 24.12
  },
  {
    "date": "2025-12-05",
    "rate": 23.12
  },
  {
    "date": "2025-12-06",
    "rate": 24.09
  },
  {
    "date": "2025-12-07",
    "rate": 24.09
  },
  {
    "date": "2025-12-08",
    "rate": 23.3
  },
  {
    "date": "2025-12-09",
    "rate": 24.14
  },
  {
    "date": "2025-12-10",
    "rate": 23.2
  },
  {
    "date": "2025-12-11",
    "rate": 23.51
  },
  {
    "date": "2025-12-12",
    "rate": 23.43
  },
  {
    "date": "2025-12-13",
    "rate": 23.43
  },
  {
    "date": "2025-12-14",
    "rate": 23.43
  },
  {
    "date": "2025-12-15",
    "rate": 23.5
  },
  {
    "date": "2025-12-16",
    "rate": 23.55
  },
  {
    "date": "2025-12-17",
    "rate": 23.31
  },
  {
    "date": "2025-12-18",
    "rate": 23.38
  },
  {
    "date": "2025-12-19",
    "rate": 23.21
  },
  {
    "date": "2025-12-20",
    "rate": 24
  },
  {
    "date": "2025-12-21",
    "rate": 24
  },
  {
    "date": "2025-12-22",
    "rate": 23.21
  },
  {
    "date": "2025-12-23",
    "rate": 23.21
  },
  {
    "date": "2025-12-24",
    "rate": 23.13
  },
  {
    "date": "2025-12-25",
    "rate": 23.13
  },
  {
    "date": "2025-12-26",
    "rate": 23.25
  },
  {
    "date": "2025-12-27",
    "rate": 23.25
  },
  {
    "date": "2025-12-28",
    "rate": 23.25
  },
  {
    "date": "2025-12-29",
    "rate": 23.26
  },
  {
    "date": "2025-12-30",
    "rate": 23.22
  },
  {
    "date": "2025-12-31",
    "rate": 23.14
  },
  {
    "date": "2026-01-01",
    "rate": 23.29
  },
  {
    "date": "2026-01-02",
    "rate": 23.34
  },
  {
    "date": "2026-01-03",
    "rate": 24.12
  },
  {
    "date": "2026-01-04",
    "rate": 24.12
  },
  {
    "date": "2026-01-05",
    "rate": 23.28
  },
  {
    "date": "2026-01-06",
    "rate": 23.42
  },
  {
    "date": "2026-01-07",
    "rate": 23.23
  },
  {
    "date": "2026-01-08",
    "rate": 23.25
  },
  {
    "date": "2026-01-09",
    "rate": 23.17
  },
  {
    "date": "2026-01-10",
    "rate": 23.17
  },
  {
    "date": "2026-01-11",
    "rate": 23.17
  },
  {
    "date": "2026-01-12",
    "rate": 23.35
  },
  {
    "date": "2026-01-13",
    "rate": 23.32
  },
  {
    "date": "2026-01-14",
    "rate": 23.19
  },
  {
    "date": "2026-01-15",
    "rate": 23.19
  },
  {
    "date": "2026-01-16",
    "rate": 23.34
  },
  {
    "date": "2026-01-17",
    "rate": 24.32
  },
  {
    "date": "2026-01-18",
    "rate": 24.32
  },
  {
    "date": "2026-01-19",
    "rate": 23.52
  },
  {
    "date": "2026-01-20",
    "rate": 23.47
  },
  {
    "date": "2026-01-21",
    "rate": 24.57
  },
  {
    "date": "2026-01-22",
    "rate": 23.61
  },
  {
    "date": "2026-01-23",
    "rate": 24.61
  },
  {
    "date": "2026-01-24",
    "rate": 24.61
  },
  {
    "date": "2026-01-25",
    "rate": 24.61
  },
  {
    "date": "2026-01-26",
    "rate": 24.61
  },
  {
    "date": "2026-01-27",
    "rate": 24.58
  },
  {
    "date": "2026-01-28",
    "rate": 23.97
  },
  {
    "date": "2026-01-29",
    "rate": 23.86
  },
  {
    "date": "2026-01-30",
    "rate": 23.73
  },
  {
    "date": "2026-01-31",
    "rate": 24.59
  },
  {
    "date": "2026-02-01",
    "rate": 24.59
  },
  {
    "date": "2026-02-02",
    "rate": 23.55
  },
  {
    "date": "2026-02-03",
    "rate": 23.17
  },
  {
    "date": "2026-02-04",
    "rate": 23.52
  },
  {
    "date": "2026-02-05",
    "rate": 24.23
  },
  {
    "date": "2026-02-06",
    "rate": 23.48
  },
  {
    "date": "2026-02-07",
    "rate": 24.27
  },
  {
    "date": "2026-02-08",
    "rate": 24.27
  },
  {
    "date": "2026-02-09",
    "rate": 23.5
  },
  {
    "date": "2026-02-10",
    "rate": 23.53
  },
  {
    "date": "2026-02-11",
    "rate": 23.41
  },
  {
    "date": "2026-02-12",
    "rate": 23.37
  },
  {
    "date": "2026-02-13",
    "rate": 23.43
  },
  {
    "date": "2026-02-14",
    "rate": 23.43
  },
  {
    "date": "2026-02-15",
    "rate": 23.43
  },
  {
    "date": "2026-02-16",
    "rate": 23.46
  },
  {
    "date": "2026-02-17",
    "rate": 23.44
  },
  {
    "date": "2026-02-18",
    "rate": 23.48
  },
  {
    "date": "2026-02-19",
    "rate": 23.48
  },
  {
    "date": "2026-02-20",
    "rate": 23.48
  },
  {
    "date": "2026-02-21",
    "rate": 24.22
  },
  {
    "date": "2026-02-22",
    "rate": 24.22
  }
]