{
  "USD": {
    "date": "2026-03-16",
    "rate": 92.03
  },
  "AED": {
    "date": "2026-03-16",
    "rate": 24.56
  },
  "AUD": {
    "date": "2026-03-16",
    "rate": 63.7
  },
  "BDT": {
    "date": "2026-03-16",
    "rate": 0
  },
  "BHD": {
    "date": "2026-03-16",
    "rate": 231.62
  },
  "CAD": {
    "date": "2026-03-16",
    "rate": 66.64
  },
  "CHF": {
    "date": "2026-03-16",
    "rate": 115.17
  },
  "CNY": {
    "date": "2026-03-16",
    "rate": 0
  },
  "DKK": {
    "date": "2026-03-16",
    "rate": 14.05
  },
  "EUR": {
    "date": "2026-03-16",
    "rate": 104.56
  },
  "GBP": {
    "date": "2026-03-16",
    "rate": 121.22
  },
  "HKD": {
    "date": "2026-03-16",
    "rate": 11.72
  },
  "JPY": {
    "date": "2026-03-16",
    "rate": 0.5734
  },
  "KES": {
    "date": "2026-03-16",
    "rate": 0
  },
  "KRW": {
    "date": "2026-03-16",
    "rate": 0
  },
  "KWD": {
    "date": "2026-03-16",
    "rate": 293.01
  },
  "LKR": {
    "date": "2026-03-16",
    "rate": 0
  },
  "MYR": {
    "date": "2026-03-16",
    "rate": 0
  },
  "NOK": {
    "date": "2026-03-16",
    "rate": 9.42
  },
  "NZD": {
    "date": "2026-03-16",
    "rate": 52.67
  },
  "OMR": {
    "date": "2026-03-16",
    "rate": 231.92
  },
  "PKR": {
    "date": "2026-03-16",
    "rate": 0
  },
  "QAR": {
    "date": "2026-03-16",
    "rate": 23.92
  },
  "RUB": {
    "date": "2026-03-16",
    "rate": 0
  },
  "SAR": {
    "date": "2026-03-16",
    "rate": 24.16
  },
  "SEK": {
    "date": "2026-03-16",
    "rate": 9.73
  },
  "SGD": {
    "date": "2026-03-16",
    "rate": 71.25
  },
  "THB": {
    "date": "2026-03-16",
    "rate": 2.6
  },
  "TRY": {
    "date": "2026-03-16",
    "rate": 0
  },
  "ZAR": {
    "date": "2026-03-16",
    "rate": 5.36
  },
  "IDR": {
    "date": "2026-03-16",
    "rate": 0
  }
}